{
    "Name": "Stage Collection",
    "Version": "1.0 Cathy1",
    "Stages": [
        {
            "Name": "Stage",
            "Platforms": [
                {
                    "Name": "Platform",
                    "Position": {
                        "x": 0,
                        "y": 0,
                        "z": 0
                    },
                    "Blocks": [
                        {
                            "Name": "faedbf5e-c57b-4432-809d-45241885930f",
                            "Palette": "Cathy1 Internal",
                            "Type": "Basic",
                            "Position": {
                                "x": -1,
                                "y": 1,
                                "z": 0
                            },
                            "Properties": [
                                {
                                    "Key": "Motion State",
                                    "Value": "Grounded"
                                }
                            ]
                        },
                        {
                            "Name": "91f17541-77da-4d9f-9214-108f1545fab5",
                            "Palette": "Cathy1 Internal",
                            "Type": "Basic",
                            "Position": {
                                "x": 0,
                                "y": 1,
                                "z": 0
                            },
                            "Properties": [
                                {
                                    "Key": "Motion State",
                                    "Value": "Grounded"
                                }
                            ]
                        },
                        {
                            "Name": "6cc62219-4405-4256-91cf-941db830347e",
                            "Palette": "Cathy1 Internal",
                            "Type": "Basic",
                            "Position": {
                                "x": 1,
                                "y": 1,
                                "z": 0
                            },
                            "Properties": [
                                {
                                    "Key": "Motion State",
                                    "Value": "Grounded"
                                }
                            ]
                        },
                        {
                            "Name": "14a91d57-1f23-4a38-a7e1-0a84ae3282c2",
                            "Palette": "Cathy1 Internal",
                            "Type": "Basic",
                            "Position": {
                                "x": 1,
                                "y": 2,
                                "z": 0
                            },
                            "Properties": [
                                {
                                    "Key": "Motion State",
                                    "Value": "Grounded"
                                }
                            ]
                        },
                        {
                            "Name": "175cb052-2963-4977-b2a5-0aaa7dad2c1c",
                            "Palette": "Cathy1 Internal",
                            "Type": "Basic",
                            "Position": {
                                "x": 0,
                                "y": 2,
                                "z": 0
                            },
                            "Properties": [
                                {
                                    "Key": "Motion State",
                                    "Value": "Grounded"
                                }
                            ]
                        },
                        {
                            "Name": "36aa5032-e82f-4c42-9283-082cc8e5554b",
                            "Palette": "Cathy1 Internal",
                            "Type": "Basic",
                            "Position": {
                                "x": -1,
                                "y": 2,
                                "z": 0
                            },
                            "Properties": [
                                {
                                    "Key": "Motion State",
                                    "Value": "Grounded"
                                }
                            ]
                        },
                        {
                            "Name": "342b9268-437a-4601-b1bf-f74120d6ec76",
                            "Palette": "Cathy1 Internal",
                            "Type": "Basic",
                            "Position": {
                                "x": -1,
                                "y": 3,
                                "z": 0
                            },
                            "Properties": [
                                {
                                    "Key": "Motion State",
                                    "Value": "Grounded"
                                }
                            ]
                        },
                        {
                            "Name": "9cb9ebc4-d439-4b9c-bc2d-60448c72a1b4",
                            "Palette": "Cathy1 Internal",
                            "Type": "Basic",
                            "Position": {
                                "x": 0,
                                "y": 3,
                                "z": 0
                            },
                            "Properties": [
                                {
                                    "Key": "Motion State",
                                    "Value": "Grounded"
                                }
                            ]
                        },
                        {
                            "Name": "88d3491f-0f5a-4874-a9cf-db6da0589c28",
                            "Palette": "Cathy1 Internal",
                            "Type": "Basic",
                            "Position": {
                                "x": 1,
                                "y": 3,
                                "z": 0
                            },
                            "Properties": [
                                {
                                    "Key": "Motion State",
                                    "Value": "Grounded"
                                }
                            ]
                        },
                        {
                            "Name": "f8fec101-883c-4994-836c-cf5118ffe0ea",
                            "Palette": "Cathy1 Internal",
                            "Type": "Basic",
                            "Position": {
                                "x": 1,
                                "y": 4,
                                "z": 1
                            },
                            "Properties": [
                                {
                                    "Key": "Motion State",
                                    "Value": "Edged"
                                }
                            ]
                        },
                        {
                            "Name": "72bd92b6-2f25-469a-beef-069ea9c04546",
                            "Palette": "Cathy1 Internal",
                            "Type": "Basic",
                            "Position": {
                                "x": 0,
                                "y": 4,
                                "z": 1
                            },
                            "Properties": [
                                {
                                    "Key": "Motion State",
                                    "Value": "Edged"
                                }
                            ]
                        },
                        {
                            "Name": "9bdcbf5e-75dc-46dc-9484-33dbdebd9cb1",
                            "Palette": "Cathy1 Internal",
                            "Type": "Basic",
                            "Position": {
                                "x": -1,
                                "y": 4,
                                "z": 1
                            },
                            "Properties": [
                                {
                                    "Key": "Motion State",
                                    "Value": "Edged"
                                }
                            ]
                        },
                        {
                            "Name": "6d419e3c-a229-462e-bdf1-47f3d50fd0cb",
                            "Palette": "Cathy1 Internal",
                            "Type": "Basic",
                            "Position": {
                                "x": -1,
                                "y": 5,
                                "z": 1
                            },
                            "Properties": [
                                {
                                    "Key": "Motion State",
                                    "Value": "Grounded"
                                }
                            ]
                        },
                        {
                            "Name": "1f942f7b-9665-4ac2-8ced-40c105df0dda",
                            "Palette": "Cathy1 Internal",
                            "Type": "Basic",
                            "Position": {
                                "x": 0,
                                "y": 5,
                                "z": 1
                            },
                            "Properties": [
                                {
                                    "Key": "Motion State",
                                    "Value": "Grounded"
                                }
                            ]
                        },
                        {
                            "Name": "63603014-6cd4-4b04-b296-8b99db81722d",
                            "Palette": "Cathy1 Internal",
                            "Type": "Basic",
                            "Position": {
                                "x": 1,
                                "y": 5,
                                "z": 1
                            },
                            "Properties": [
                                {
                                    "Key": "Motion State",
                                    "Value": "Grounded"
                                }
                            ]
                        },
                        {
                            "Name": "24f7897b-df34-44ee-93bb-2940210c8cc9",
                            "Palette": "Cathy1 Internal",
                            "Type": "Basic",
                            "Position": {
                                "x": 0,
                                "y": 6,
                                "z": 1
                            },
                            "Properties": [
                                {
                                    "Key": "Motion State",
                                    "Value": "Grounded"
                                }
                            ]
                        },
                        {
                            "Name": "8312ee39-3cdd-4a3b-bee2-a394ba18ee72",
                            "Palette": "Cathy1 Internal",
                            "Type": "Basic",
                            "Position": {
                                "x": 1,
                                "y": 6,
                                "z": 2
                            },
                            "Properties": [
                                {
                                    "Key": "Motion State",
                                    "Value": "Edged"
                                }
                            ]
                        },
                        {
                            "Name": "10632dea-d9d1-414f-a8c6-8883b9f44f1e",
                            "Palette": "Cathy1 Internal",
                            "Type": "Basic",
                            "Position": {
                                "x": -1,
                                "y": 6,
                                "z": 2
                            },
                            "Properties": [
                                {
                                    "Key": "Motion State",
                                    "Value": "Edged"
                                }
                            ]
                        },
                        {
                            "Name": "cdb887fe-3504-4957-a5b7-e04c9f088497",
                            "Palette": "Cathy1 Internal",
                            "Type": "Basic",
                            "Position": {
                                "x": -1,
                                "y": 7,
                                "z": 2
                            },
                            "Properties": [
                                {
                                    "Key": "Motion State",
                                    "Value": "Grounded"
                                }
                            ]
                        },
                        {
                            "Name": "5906fd5b-860f-4a08-b87f-fa50aa1bbeff",
                            "Palette": "Cathy1 Internal",
                            "Type": "Basic",
                            "Position": {
                                "x": 0,
                                "y": 7,
                                "z": 2
                            },
                            "Properties": [
                                {
                                    "Key": "Motion State",
                                    "Value": "Edged"
                                }
                            ]
                        },
                        {
                            "Name": "8971526e-4b67-4aa4-8598-de9eaf9fa57c",
                            "Palette": "Cathy1 Internal",
                            "Type": "Basic",
                            "Position": {
                                "x": 1,
                                "y": 7,
                                "z": 2
                            },
                            "Properties": [
                                {
                                    "Key": "Motion State",
                                    "Value": "Grounded"
                                }
                            ]
                        },
                        {
                            "Name": "4ac1a032-aee7-423b-9d79-e05696bc62d3",
                            "Palette": "Cathy1 Internal",
                            "Type": "Basic",
                            "Position": {
                                "x": 2,
                                "y": 7,
                                "z": 2
                            },
                            "Properties": [
                                {
                                    "Key": "Motion State",
                                    "Value": "Edged"
                                }
                            ]
                        },
                        {
                            "Name": "505a9121-4b18-48f4-a12c-64dd79e50bde",
                            "Palette": "Cathy1 Internal",
                            "Type": "Basic",
                            "Position": {
                                "x": 1,
                                "y": 4,
                                "z": 0
                            },
                            "Properties": [
                                {
                                    "Key": "Motion State",
                                    "Value": "Grounded"
                                }
                            ]
                        },
                        {
                            "Name": "efa23393-a07e-406a-8927-91e4ed1aeca6",
                            "Palette": "Cathy1 Internal",
                            "Type": "Basic",
                            "Position": {
                                "x": -2,
                                "y": 7,
                                "z": 2
                            },
                            "Properties": [
                                {
                                    "Key": "Motion State",
                                    "Value": "Edged"
                                }
                            ]
                        },
                        {
                            "Name": "c233de76-0b83-494b-9407-016573bf48e5",
                            "Palette": "Cathy1 Internal",
                            "Type": "Basic",
                            "Position": {
                                "x": -1,
                                "y": 8,
                                "z": 2
                            },
                            "Properties": [
                                {
                                    "Key": "Motion State",
                                    "Value": "Grounded"
                                }
                            ]
                        },
                        {
                            "Name": "d33dd51e-931d-413a-9dd2-ea8b4df82480",
                            "Palette": "Cathy1 Internal",
                            "Type": "Basic",
                            "Position": {
                                "x": 0,
                                "y": 8,
                                "z": 2
                            },
                            "Properties": [
                                {
                                    "Key": "Motion State",
                                    "Value": "Grounded"
                                }
                            ]
                        },
                        {
                            "Name": "0643fa75-5c01-48d6-84c0-0839917eeba6",
                            "Palette": "Cathy1 Internal",
                            "Type": "Basic",
                            "Position": {
                                "x": 1,
                                "y": 8,
                                "z": 2
                            },
                            "Properties": [
                                {
                                    "Key": "Motion State",
                                    "Value": "Grounded"
                                }
                            ]
                        },
                        {
                            "Name": "887bad3c-2522-4186-97cb-be52189e145a",
                            "Palette": "Cathy1 Internal",
                            "Type": "Goal",
                            "Position": {
                                "x": 0,
                                "y": 9,
                                "z": 2
                            },
                            "Properties": [
                                {
                                    "Key": "Motion State",
                                    "Value": "Grounded"
                                },
                                {
                                    "Key": "Weight Factor",
                                    "Value": "0"
                                }
                            ]
                        }
                    ],
                    "Items": null,
                    "Events": [
                        {
                            "Name": "a490c396-7596-4650-b395-7a0a48c29ee4",
                            "Palette": "Cathy1 Internal",
                            "Type": "Player Start",
                            "Position": {
                                "x": -1,
                                "y": 3.5,
                                "z": 0
                            },
                            "Properties": [
                                {
                                    "Key": "PlayerNumber",
                                    "Value": "0"
                                }
                            ]
                        }
                    ]
                }
            ]
        }
    ]
}